toston/__init__.py
toston/cli.py
toston/toston.py
toston-0.2.0.dist-info/DESCRIPTION.rst
toston-0.2.0.dist-info/METADATA
toston-0.2.0.dist-info/RECORD
toston-0.2.0.dist-info/WHEEL
toston-0.2.0.dist-info/entry_points.txt
toston-0.2.0.dist-info/metadata.json
toston-0.2.0.dist-info/top_level.txt
