Metadata-Version: 2.0
Name: toston
Version: 0.2.0
Summary: Toston generates a secret key with size variable (in bytes)
Home-page: https://github.com/joseamaita/toston
Author: José A. Maita
Author-email: jose_a_maita@hotmail.com
License: MIT license
Keywords: toston
Platform: UNKNOWN
Classifier: Development Status :: 2 - Pre-Alpha
Classifier: Intended Audience :: Developers
Classifier: License :: OSI Approved :: MIT License
Classifier: Natural Language :: English
Classifier: Programming Language :: Python :: 2
Classifier: Programming Language :: Python :: 2.7
Classifier: Programming Language :: Python :: 3
Classifier: Programming Language :: Python :: 3.4
Classifier: Programming Language :: Python :: 3.5
Classifier: Programming Language :: Python :: 3.6
Requires-Dist: Click (>=6.0)
